opi_optimum/configuration_utils.py
opi_optimum/conftest.py
opi_optimum/modeling_base.py
opi_optimum/quantization_base.py
opi_optimum/runs_base.py
opi_optimum/subpackages.py
opi_optimum/version.py
opi_optimum/bettertransformer/__init__.py
opi_optimum/bettertransformer/transformation.py
opi_optimum/bettertransformer/models/__init__.py
opi_optimum/bettertransformer/models/attention.py
opi_optimum/bettertransformer/models/base.py
opi_optimum/bettertransformer/models/decoder_models.py
opi_optimum/bettertransformer/models/encoder_models.py
opi_optimum/commands/__init__.py
opi_optimum/commands/base.py
opi_optimum/commands/env.py
opi_optimum/commands/optimum_cli.py
opi_optimum/commands/export/__init__.py
opi_optimum/commands/register/__init__.py
opi_optimum/utils/__init__.py
opi_optimum/utils/constant.py
opi_optimum/utils/doc.py
opi_optimum/utils/dummy_bettertransformer_objects.py
opi_optimum/utils/dummy_diffusers_objects.py
opi_optimum/utils/file_utils.py
opi_optimum/utils/import_utils.py
opi_optimum/utils/input_generators.py
opi_optimum/utils/logging.py
opi_optimum/utils/modeling_utils.py
opi_optimum/utils/normalized_config.py
opi_optimum/utils/runs.py
opi_optimum/utils/save_utils.py
opi_optimum/utils/testing_utils.py
opi_optimum/utils/preprocessing/__init__.py
opi_optimum/utils/preprocessing/base.py
opi_optimum/utils/preprocessing/image_classification.py
opi_optimum/utils/preprocessing/question_answering.py
opi_optimum/utils/preprocessing/task_processors_manager.py
opi_optimum/utils/preprocessing/text_classification.py
opi_optimum/utils/preprocessing/token_classification.py
opi_optimum-1.26.3.dev0.dist-info/licenses/LICENSE
opi_optimum-1.26.3.dev0.dist-info/METADATA
opi_optimum-1.26.3.dev0.dist-info/WHEEL
opi_optimum-1.26.3.dev0.dist-info/entry_points.txt
opi_optimum-1.26.3.dev0.dist-info/top_level.txt
opi_optimum-1.26.3.dev0.dist-info/RECORD
