Metadata-Version: 2.4
Name: opi_optimum
Version: 1.26.3.dev0
Summary: Optimum Library is an extension of the Hugging Face Transformers library, providing a framework to integrate third-party libraries from Hardware Partners and interface with their specific functionality.
Author: HuggingFace Inc. Special Ops Team
Author-email: hardware@huggingface.co
License: Apache
Requires-Python: >=3.9.0
License-File: LICENSE
Requires-Dist: torch>=1.11
Requires-Dist: numpy
Requires-Dist: huggingface_hub>=0.8.0
Requires-Dist: datasets
Dynamic: author
Dynamic: author-email
Dynamic: description
Dynamic: description-content-type
Dynamic: license
Dynamic: license-file
Dynamic: requires-dist
Dynamic: requires-python
Dynamic: summary
